aoc/__init__.py
aoc/file/__init__.py
aoc/file/loaddata.py
ccb_aoc_tools-2024.12.1.2.dist-info/LICENSE.txt
ccb_aoc_tools-2024.12.1.2.dist-info/METADATA
ccb_aoc_tools-2024.12.1.2.dist-info/WHEEL
ccb_aoc_tools-2024.12.1.2.dist-info/top_level.txt
ccb_aoc_tools-2024.12.1.2.dist-info/RECORD
