Metadata-Version: 2.1
Name: ccb_aoc_tools
Version: 2024.12.1.2
Summary: My custom-made tools for Advent of Code projects.
Author-email: Elijah Underhill <elijahmcraft6@gmail.com>
Classifier: License :: OSI Approved :: MIT License
Classifier: Programming Language :: Python
Requires-Python: >=3.4
License-File: LICENSE.txt
